{
  ".svelte-kit/build/index.js": {
    "file": "index.js",
    "src": ".svelte-kit/build/index.js",
    "isEntry": true,
    "imports": [
      "_index.js"
    ],
    "dynamicImports": [
      ".svelte-kit/build/hooks.js"
    ]
  },
  "node_modules/@sveltejs/kit/src/runtime/components/layout.svelte": {
    "file": "entries/fallbacks/layout.svelte.js",
    "src": "node_modules/@sveltejs/kit/src/runtime/components/layout.svelte",
    "isEntry": true,
    "imports": [
      "_index.js"
    ]
  },
  "src/routes/+layout.js": {
    "file": "entries/pages/_layout.js",
    "src": "src/routes/+layout.js",
    "isEntry": true
  },
  "node_modules/@sveltejs/kit/src/runtime/components/error.svelte": {
    "file": "entries/fallbacks/error.svelte.js",
    "src": "node_modules/@sveltejs/kit/src/runtime/components/error.svelte",
    "isEntry": true,
    "imports": [
      "_index.js"
    ]
  },
  "src/routes/app/+layout.svelte": {
    "file": "entries/pages/app/_layout.svelte.js",
    "src": "src/routes/app/+layout.svelte",
    "isEntry": true,
    "imports": [
      "_index.js"
    ]
  },
  "src/routes/+page.svelte": {
    "file": "entries/pages/_page.svelte.js",
    "src": "src/routes/+page.svelte",
    "isEntry": true,
    "imports": [
      "_index.js"
    ]
  },
  "src/routes/app/+page.svelte": {
    "file": "entries/pages/app/_page.svelte.js",
    "src": "src/routes/app/+page.svelte",
    "isEntry": true,
    "imports": [
      "_index.js"
    ]
  },
  "src/routes/app/contracts/+page.svelte": {
    "file": "entries/pages/app/contracts/_page.svelte.js",
    "src": "src/routes/app/contracts/+page.svelte",
    "isEntry": true,
    "imports": [
      "_index.js"
    ]
  },
  "_index.js": {
    "file": "chunks/index.js"
  },
  ".svelte-kit/build/hooks.js": {
    "file": "chunks/hooks.js",
    "src": ".svelte-kit/build/hooks.js",
    "isDynamicEntry": true
  }
}